{"expireTime":9007200813799435000,"key":"transformer-remark-markdown-html-ast-3443f13f0e6eda6dcb529808696407d9-gatsby-remark-images-","val":{"type":"root","children":[{"type":"element","tagName":"p","properties":{},"children":[{"type":"text","value":"Here's yet another blog post. Number four.","position":{"start":{"line":2,"column":1,"offset":1},"end":{"line":2,"column":43,"offset":43}}}],"position":{"start":{"line":2,"column":1,"offset":1},"end":{"line":2,"column":43,"offset":43}}}],"position":{"start":{"line":1,"column":1,"offset":0},"end":{"line":3,"column":1,"offset":44}}}}